imagetoolkit/__init__.py
imagetoolkit/addtext.py
imagetoolkit/cli.py
imagetoolkit/color.py
imagetoolkit/compress.py
imagetoolkit/extension.py
imagetoolkit/imagetoolkit.py
imagetoolkit/rescale.py
imagetoolkit/utils.py
imagetoolkit/variables.py
imagetoolkit-0.1.1.dist-info/LICENSE
imagetoolkit-0.1.1.dist-info/METADATA
imagetoolkit-0.1.1.dist-info/WHEEL
imagetoolkit-0.1.1.dist-info/entry_points.txt
imagetoolkit-0.1.1.dist-info/top_level.txt
imagetoolkit-0.1.1.dist-info/RECORD
